any4any-0.1.1.dist-info/licenses/LICENSE
core/__init__.py
core/lifespan.py
core/log.py
core/model_manager.py
core/asr/transcription.py
core/auth/model_auth.py
core/chat/conversation_database.py
core/chat/conversation_manager.py
core/chat/delay_manager.py
core/chat/llm.py
core/chat/openai_api.py
core/chat/preview.py
core/database/database.py
core/dingtalk/message_manager.py
core/embedding/document_processor.py
core/embedding/embedding_manager.py
core/embedding/kb_server.py
core/embedding/openai_api.py
core/embedding/retrieval_engine.py
core/embedding/vector_store.py
core/mcp/mcp_tools.py
core/rerank/rerank.py
core/tts/file.py
core/tts/index_tts_engine.py
core/tts/speech.py
core/tts/indextts/__init__.py
core/tts/indextts/cli.py
core/tts/indextts/infer.py
core/tts/indextts/BigVGAN/ECAPA_TDNN.py
core/tts/indextts/BigVGAN/__init__.py
core/tts/indextts/BigVGAN/activations.py
core/tts/indextts/BigVGAN/bigvgan.py
core/tts/indextts/BigVGAN/models.py
core/tts/indextts/BigVGAN/utils.py
core/tts/indextts/BigVGAN/alias_free_activation/__init__.py
core/tts/indextts/BigVGAN/alias_free_activation/cuda/__init__.py
core/tts/indextts/BigVGAN/alias_free_activation/cuda/activation1d.py
core/tts/indextts/BigVGAN/alias_free_activation/cuda/load.py
core/tts/indextts/BigVGAN/alias_free_activation/torch/__init__.py
core/tts/indextts/BigVGAN/alias_free_activation/torch/act.py
core/tts/indextts/BigVGAN/alias_free_activation/torch/filter.py
core/tts/indextts/BigVGAN/alias_free_activation/torch/resample.py
core/tts/indextts/BigVGAN/alias_free_torch/__init__.py
core/tts/indextts/BigVGAN/alias_free_torch/act.py
core/tts/indextts/BigVGAN/alias_free_torch/filter.py
core/tts/indextts/BigVGAN/alias_free_torch/resample.py
core/tts/indextts/BigVGAN/nnet/CNN.py
core/tts/indextts/BigVGAN/nnet/__init__.py
core/tts/indextts/BigVGAN/nnet/linear.py
core/tts/indextts/BigVGAN/nnet/normalization.py
core/tts/indextts/gpt/__init__.py
core/tts/indextts/gpt/conformer_encoder.py
core/tts/indextts/gpt/model.py
core/tts/indextts/gpt/perceiver.py
any4any-0.1.1.dist-info/METADATA
any4any-0.1.1.dist-info/WHEEL
any4any-0.1.1.dist-info/entry_points.txt
any4any-0.1.1.dist-info/top_level.txt
any4any-0.1.1.dist-info/RECORD
