Metadata-Version: 2.4
Name: any4any
Version: 0.1.1
Summary: 大模型会话、对话内容预览与修改、语音识别、文本转语音、文档重排、文本嵌入、知识库系统和MCP服务的一键式API服务
Author-email: eogee <eogee@qq.com>
License: MIT License
Project-URL: Homepage, https://eogee.com
Project-URL: Source, https://github.com/eogee/any4any
Project-URL: Documentation, https://github.com/eogee/any4any/tree/master/docs
Project-URL: Issues, https://github.com/eogee/any4any/issues
Project-URL: Repository, https://github.com/eogee/any4any
Keywords: AI,ML,ASR,LLM,TTS,RERANK,EMBEDDING
Classifier: Development Status :: 3 - Alpha
Classifier: Intended Audience :: Developers
Classifier: Intended Audience :: End Users/Desktop
Classifier: Programming Language :: Python :: 3
Classifier: Programming Language :: Python :: 3.8
Classifier: Programming Language :: Python :: 3.9
Classifier: Programming Language :: Python :: 3.10
Classifier: License :: OSI Approved :: MIT License
Classifier: Operating System :: OS Independent
Requires-Python: >=3.10
License-File: LICENSE
Requires-Dist: edge-tts
Requires-Dist: torch==2.3
Requires-Dist: torchaudio
Requires-Dist: funasr>=1.1.3
Requires-Dist: fastapi>=0.111.1
Requires-Dist: uvicorn
Requires-Dist: python-dotenv
Requires-Dist: transformers==4.51.0
Requires-Dist: FlagEmbedding==1.2.3
Requires-Dist: pydantic>=2.0.0
Requires-Dist: mysql-connector-python>=8.1.0
Requires-Dist: FastMCP
Requires-Dist: dingtalk_stream
Requires-Dist: alibabacloud_dingtalk
Requires-Dist: numpy>=1.21.0
Requires-Dist: sentence-transformers>=2.2.0
Requires-Dist: requests>=2.25.0
Requires-Dist: PyPDF2>=1.27.0
Requires-Dist: python-docx>=0.8.11
Requires-Dist: chardet>=4.0.0
Requires-Dist: chromadb>=0.2.0
Requires-Dist: itsdangerous>=2.1.2
Requires-Dist: matplotlib
Requires-Dist: omegaconf
Requires-Dist: tqdm
Requires-Dist: pyyaml
Requires-Dist: deepspeed
Requires-Dist: sentencepiece
Requires-Dist: einops
Requires-Dist: scipy
Requires-Dist: soundfile
Requires-Dist: packaging
Requires-Dist: huggingface_hub
Requires-Dist: WeTextProcessing; platform_machine != "Darwin"
Requires-Dist: wetext; platform_system == "Darwin"
Dynamic: license-file
